text_to_action/__init__.py
text_to_action/create_actions.py
text_to_action/entity_models.py
text_to_action/example_actions/calculator/descriptions.json
text_to_action/example_actions/calculator/embeddings.h5
text_to_action/example_actions/calculator/implementation.py
text_to_action/example_actions/on_device.py
text_to_action/extract_parameters.py
text_to_action/llm_utils.py
text_to_action/main.py
text_to_action/types.py
text_to_action/utils.py
text_to_action/vector_emb.py
text_to_action-2.0.2.dist-info/LICENSE
text_to_action-2.0.2.dist-info/METADATA
text_to_action-2.0.2.dist-info/WHEEL
text_to_action-2.0.2.dist-info/RECORD
