Metadata-Version: 2.1
Name: text_to_action
Version: 2.0.2
Summary: A system that translates natural language queries into programmatic actions
Home-page: https://github.com/sri0606/text_to_action
License: MIT
Keywords: text_to_action,function calling,natural language processing,automation
Author: Sriram Seelamneni
Author-email: srirams0606@gmail.com
Requires-Python: >=3.8,<4.0
Classifier: License :: OSI Approved :: MIT License
Classifier: Programming Language :: Python
Classifier: Programming Language :: Python :: 3
Classifier: Programming Language :: Python :: 3.8
Classifier: Programming Language :: Python :: 3.9
Classifier: Programming Language :: Python :: 3.10
Classifier: Programming Language :: Python :: 3.11
Requires-Dist: deepdiff
Requires-Dist: groq
Requires-Dist: h5py
Requires-Dist: litellm
Requires-Dist: matplotlib
Requires-Dist: numpy
Requires-Dist: openai
Requires-Dist: pydantic
Requires-Dist: python-dotenv
Requires-Dist: python_dateutil
Requires-Dist: scipy
Requires-Dist: sentence-transformers
Requires-Dist: spacy
Requires-Dist: torch
Requires-Dist: transformers
Project-URL: Repository, https://github.com/sri0606/text_to_action
